{
    "swagger": "2.0",
    "info": {
        "contact": {
            "name": "API Support",
            "url": "http://www.swagger.io/support",
            "email": "support@swagger.io"
        },
        "license": {
            "name": "Apache 2.0",
            "url": "http://www.apache.org/licenses/LICENSE-2.0.html"
        }
    },
    "paths": {
        "/users/GetUsers": {
            "get": {
                "description": "Get AllUsers",
                "consumes": [
                    "application/json"
                ],
                "produces": [
                    "application/json"
                ],
                "tags": [
                    "Users"
                ],
                "summary": "Get Users",
                "responses": {
                    "200": {
                        "description": "OK",
                        "schema": {
                            "$ref": "#/definitions/models.Users"
                        }
                    }
                }
            }
        }
    },
    "definitions": {
        "models.Users": {
            "type": "object",
            "properties": {
                "age": {
                    "type": "integer"
                },
                "city": {
                    "type": "string"
                },
                "email": {
                    "type": "string"
                },
                "firstname": {
                    "type": "string"
                },
                "id": {
                    "type": "string"
                },
                "lastname": {
                    "type": "number"
                },
                "password": {
                    "type": "string"
                }
            }
        }
    }
}